whispercppy-0.0.4.dist-info/METADATA
whispercppy-0.0.4.dist-info/LICENSE
whispercppy-0.0.4.dist-info/WHEEL
whispercppy-0.0.4.dist-info/top_level.txt
whispercppy-0.0.4.dist-info/RECORD
whispercppy/__init__.py
whispercppy/libwhisper.so
whispercppy/api_cpp2py_export.cpython-311-x86_64-linux-gnu.so
whispercppy/__init__.pyi
whispercppy/api.pyi
whispercppy/utils.py
whispercppy/py.typed
