Metadata-Version: 2.1
Name: whispercppy
Version: 0.0.4
Summary: Python bindings for whisper.cpp
Home-page: https://github.com/pajowu/whispercppy
Author: pajowu
Author-email: git@ca.pajowu.de
Requires-Python: >=3.7
License-File: LICENSE
